photonsphinx/__init__.py
photonsphinx/_version.py
photonsphinx/about.html
photonsphinx/donate.html
photonsphinx/layout.html
photonsphinx/navigation.html
photonsphinx/relations.html
photonsphinx/support.py
photonsphinx/theme.conf
photonsphinx/__pycache__/__init__.cpython-39.pyc
photonsphinx/__pycache__/_version.cpython-39.pyc
photonsphinx/static/custom.css
photonsphinx/static/photonsphinx.css_t
photonsphinx-0.0.1.dist-info/LICENSE
photonsphinx-0.0.1.dist-info/METADATA
photonsphinx-0.0.1.dist-info/WHEEL
photonsphinx-0.0.1.dist-info/entry_points.txt
photonsphinx-0.0.1.dist-info/top_level.txt
photonsphinx-0.0.1.dist-info/RECORD
